structured_light/__init__.py
structured_light/structures.py
structured_light/utils.py
structured_light/zernike.py
structured_light-0.1.0.dist-info/METADATA
structured_light-0.1.0.dist-info/WHEEL
structured_light-0.1.0.dist-info/RECORD
