Metadata-Version: 2.1
Name: structured-light
Version: 0.1.0
Summary: 
Author: marcsgil
Author-email: marcosgildeoliveira@gmail.com
Requires-Python: >=3.9,<4.0
Classifier: Programming Language :: Python :: 3
Classifier: Programming Language :: Python :: 3.9
Classifier: Programming Language :: Python :: 3.10
Classifier: Programming Language :: Python :: 3.11
Classifier: Programming Language :: Python :: 3.12
Requires-Dist: numpy (>=1.23,<2.0)
Requires-Dist: scipy (>=1.9,<2.0)
